ffxpy/__init__.py
ffxpy/__main__.py
ffxpy/const.py
ffxpy/context.py
ffxpy/models/flow.py
ffxpy/setting.py
ffxpy/vendor/async_typer.py
ffxpy-0.1.0.dist-info/WHEEL
ffxpy-0.1.0.dist-info/entry_points.txt
ffxpy-0.1.0.dist-info/METADATA
ffxpy-0.1.0.dist-info/RECORD
