Metadata-Version: 2.3
Name: ffxpy
Version: 0.1.0
Summary: A project designed to simplify complex ffmpeg operations by providing a more user-friendly interface and workflow.
Author: chesham
Author-email: chesham <c.moweb@gmail.com>
License: The MIT License (MIT)
Requires-Dist: dateutils>=0.6.12
Requires-Dist: isodate>=0.7.2
Requires-Dist: pydantic-settings>=2.12.0
Requires-Dist: pyyaml>=6.0.3
Requires-Dist: typer>=0.21.1
Requires-Python: >=3.13
